requirements/__init__.py
requirements/base.txt
requirements/test.txt
vyked/__init__.py
vyked/bus.py
vyked/exceptions.py
vyked/host.py
vyked/jsonprotocol.py
vyked/packet.py
vyked/pinger.py
vyked/protocol_factory.py
vyked/pubsub.py
vyked/registry.py
vyked/registry_client.py
vyked/registry_new.py
vyked/sendqueue.py
vyked/services.py
vyked/wrappers.py
vyked/decorators/__init__.py
vyked/decorators/http.py
vyked/decorators/tcp.py
vyked/utils/__init__.py
vyked/utils/jsonencoder.py
vyked/utils/log.py
vyked/utils/ordered_class_member.py
vyked/utils/stats.py
vyked-2.1.73.dist-info/DESCRIPTION.rst
vyked-2.1.73.dist-info/METADATA
vyked-2.1.73.dist-info/metadata.json
vyked-2.1.73.dist-info/pbr.json
vyked-2.1.73.dist-info/RECORD
vyked-2.1.73.dist-info/top_level.txt
vyked-2.1.73.dist-info/WHEEL
