Metadata-Version: 2.0
Name: vyked
Version: 2.1.73
Summary: A micro-service framework for Python
Home-page: https://github.com/kashifrazzaqui/vyked
Author: Kashif Razzaqui, Ankit Chandawala
Author-email: kashif.razzaqui@gmail.com, ankitchandawala@gmail.com
License: UNKNOWN
Platform: UNKNOWN
Requires-Dist: setuptools (>=18.0)
Requires-Dist: again (==1.2.21)
Requires-Dist: aiohttp (>=0.17.0)
Requires-Dist: aiopgx (==0.7.0)
Requires-Dist: async-retrial (>0.2)
Requires-Dist: asyncio-redis (==0.13.4)
Requires-Dist: setproctitle (==1.1.8)
Requires-Dist: jsonstreamer (>=1.3.5)
Requires-Dist: flake8 (==2.4.1)
Requires-Dist: pep8 (==1.5.7)
Requires-Dist: pyflakes (==0.8.1)
Requires-Dist: wheel (==0.24.0)
Requires-Dist: pytest (==2.7.2)
Requires-Dist: factory-boy (==2.5.2)
Requires-Dist: python-json-logger (==0.1.2)
Requires-Dist: PyYAML (==3.11)
